README.rst
setup.py
micropython_nodewire.egg-info/PKG-INFO
micropython_nodewire.egg-info/SOURCES.txt
micropython_nodewire.egg-info/dependency_links.txt
micropython_nodewire.egg-info/not-zip-safe
micropython_nodewire.egg-info/requires.txt
micropython_nodewire.egg-info/top_level.txt
nodewire/__init__.py
nodewire/client.py
nodewire/control.py
nodewire/db.py
nodewire/nodewire.py
nodewire/queue.py
nodewire/splitter.py