Metadata-Version: 1.0
Name: micropython-nodewire
Version: 1.1.0
Summary: NodeWire
Home-page: http://www.nodewire.org
Author: Ahmad Sadiq
Author-email: sadiq.a.ahmad@gmail.com
License: BSD
Platform: UNKNOWN
